operagents/__init__.py
operagents/__main__.py
operagents/agent/__init__.py
operagents/agent/memory.py
operagents/backend/__init__.py
operagents/backend/_base.py
operagents/backend/openai.py
operagents/backend/user.py
operagents/character/__init__.py
operagents/cli/__init__.py
operagents/config/__init__.py
operagents/config/const.py
operagents/director/__init__.py
operagents/director/_base.py
operagents/director/model.py
operagents/director/never.py
operagents/director/user.py
operagents/exception.py
operagents/flow/__init__.py
operagents/flow/_base.py
operagents/flow/model.py
operagents/flow/order.py
operagents/flow/user.py
operagents/hook/__init__.py
operagents/hook/_base.py
operagents/hook/summary.py
operagents/log.py
operagents/opera/__init__.py
operagents/prop/__init__.py
operagents/prop/_base.py
operagents/prop/function.py
operagents/scene/__init__.py
operagents/scene/prepare/__init__.py
operagents/scene/prepare/_base.py
operagents/scene/prepare/function.py
operagents/scene/prepare/preface.py
operagents/timeline/__init__.py
operagents/timeline/event.py
operagents/utils.py
operagents/version.py
operagents-0.0.15.dist-info/LICENSE
operagents-0.0.15.dist-info/METADATA
operagents-0.0.15.dist-info/WHEEL
operagents-0.0.15.dist-info/entry_points.txt
operagents-0.0.15.dist-info/RECORD
