Metadata-Version: 2.1
Name: operagents
Version: 0.0.15
Summary: Dynamic, highly customizable language agents framework
License: MIT
Keywords: agent,llm,langchain,sop,langgraph
Author: yanyongyu
Author-email: yyy@yyydl.top
Requires-Python: >=3.10,<4.0
Classifier: License :: OSI Approved :: MIT License
Classifier: Programming Language :: Python :: 3
Classifier: Programming Language :: Python :: 3.10
Classifier: Programming Language :: Python :: 3.11
Classifier: Programming Language :: Python :: 3.12
Requires-Dist: jinja2 (>=3.1.3,<4.0.0)
Requires-Dist: loguru (>=0.7.2,<0.8.0)
Requires-Dist: noneprompt (>=0.1.9,<0.2.0)
Requires-Dist: openai (>=1.13.3,<2.0.0)
Requires-Dist: pydantic (>=2.6.3,<3.0.0)
Requires-Dist: pyyaml (>=6.0.1,<7.0.0)
Requires-Dist: rich (>=13.7.1,<14.0.0)
Requires-Dist: typing-extensions (>=4.10.0,<5.0.0)
